fustor_source_elasticsearch/__init__.py
fustor_source_elasticsearch/py.typed
fustor_source_elasticsearch-0.2.16.dist-info/METADATA
fustor_source_elasticsearch-0.2.16.dist-info/WHEEL
fustor_source_elasticsearch-0.2.16.dist-info/entry_points.txt
fustor_source_elasticsearch-0.2.16.dist-info/top_level.txt
fustor_source_elasticsearch-0.2.16.dist-info/RECORD
