Metadata-Version: 2.4
Name: fustor-source-elasticsearch
Version: 0.2.16
Summary: An Elasticsearch source for Fustor Agent
Author-email: Huajin Wang <wanghuajin999@163.com>
Requires-Python: >=3.11
Requires-Dist: elasticsearch>=9.2.0
Requires-Dist: fustor-core
